{
    "name": "Amazing Chillhop",
    "description": {
        "en": {
            "description": "Amazing Chillhop is a radio station perfect for relaxing while studying or working out! Hip hop merges with electronic music, and the beat merges with the synths, in our fantastic radio, which will accompany your days faithfully.",
            "slogan": "Work hard, Chillhop harder!"
        },
        "de": {
            "description": "lorem ipsum na germanski",
            "slogan": "Slusajte"
        },
        "fr": {
            "description": "lorem ipsum na francuski",
            "slogan": "Slusajte"
        },
        "mk": {
            "description": "lorem ipsum na makedonski",
            "slogan": "Slusajte"
        }
    }
}